alibabacloud_aisearch20230101/__init__.py
alibabacloud_aisearch20230101/client.py
alibabacloud_aisearch20230101/models.py
alibabacloud_aisearch20230101_py2-1.0.1.dist-info/LICENSE
alibabacloud_aisearch20230101_py2-1.0.1.dist-info/METADATA
alibabacloud_aisearch20230101_py2-1.0.1.dist-info/WHEEL
alibabacloud_aisearch20230101_py2-1.0.1.dist-info/top_level.txt
alibabacloud_aisearch20230101_py2-1.0.1.dist-info/RECORD
